[
  {
    "id": 0,
    "name": "Stegosaurus",
    "picture": "images/dino1.jpg"
  },
  {
    "id": 1,
    "name": "Brachiosaurus",
    "picture": "images/dino2.jpg"
  },
  {
    "id": 2,
    "name": "Spinosaurus",
    "picture": "images/dino3.jpg"
  },
  {
    "id": 3,
    "name": "Pteranodon",
    "picture": "images/dino4.jpg"
  },
  {
    "id": 4,
    "name": "Velociraptor",
    "picture": "images/dino5.jpg"
  },
  {
    "id": 5,
    "name": "Dino Eggs",
    "picture": "images/dino6.jpg"
  },
  {
    "id": 6,
    "name": "Spinosaurus",
    "picture": "images/dino3.jpg"
  },
  {
    "id": 7,
    "name": "Stegosaurus",
    "picture": "images/dino1.jpg"
  },
  {
    "id": 8,
    "name": "Brachiosaurus",
    "picture": "images/dino2.jpg"
  }
]
